setup.py
pypository/Directory.py
pypository/List.py
pypository/Loader.py
pypository/Repository.py
pypository/__init__.py
pypository/utils.py
pypository.egg-info/PKG-INFO
pypository.egg-info/SOURCES.txt
pypository.egg-info/dependency_links.txt
pypository.egg-info/top_level.txt
pypository/search/Indexer.py
pypository/search/Query.py
pypository/search/Searcher.py
pypository/search/__init__.py