Metadata-Version: 1.0
Name: pypository
Version: 0.2.0
Summary: Repository library for python objects
Home-page: https://github.com/nesaro/pypository
Author: Nestor Arocha
Author-email: nesaro@gmail.com
License: UNKNOWN
Platform: UNKNOWN
